kf_utils/__init__.py
kf_utils/__version__.py
kf_utils/char_codec.py
kf_utils/dicts.py
kf_utils/extractors.py
kf_utils/files.py
kf_utils/graphs.py
kf_utils/hashers.py
kf_utils/lang.py
kf_utils/lists.py
kf_utils/replacers.py
kf_utils/strings.py
kf_utils/timers.py
kf_utils/data_types/__init__.py
kf_utils/data_types/persistor_type.py
kf_utils/data_types/uri.py
kf_utils_package-2.0.2.dist-info/LICENSE.md
kf_utils_package-2.0.2.dist-info/METADATA
kf_utils_package-2.0.2.dist-info/WHEEL
kf_utils_package-2.0.2.dist-info/top_level.txt
kf_utils_package-2.0.2.dist-info/RECORD
