Metadata-Version: 2.1
Name: kf-utils-package
Version: 2.0.2
Summary: Utils package used in all Knowledge Factory microservices.
Home-page: https://umane.everis.com/git/KFSEMBU/utils
Download-URL: https://pypi.org/project/kf-utils-package/
Author: KFSEMBU
Maintainer: KFSEMBU
License: GNU General Public License version 3
Keywords: kfsembu,knowledge-factory,helpers,utils,utilities,useful-methods
Classifier: Programming Language :: Python :: 3
Classifier: License :: OSI Approved :: GNU General Public License v3 (GPLv3)
Classifier: Operating System :: OS Independent
Classifier: Development Status :: 5 - Production/Stable
Classifier: Framework :: Flask
Classifier: Topic :: Utilities
Requires-Python: >=3.6
License-File: LICENSE.md
Requires-Dist: validators (>=0.20.0)
Requires-Dist: urllib3 (<1.27,>=1.21.1)
Requires-Dist: file-read-backwards (>=2.0.0)
Requires-Dist: Unidecode (>=1.3.3)
Requires-Dist: rdflib (==6.1.1)
Requires-Dist: pandas (>=1.4.3)
Requires-Dist: PyYAML (>=5.1.1)
Requires-Dist: tzdata (>=2022.1)
Requires-Dist: Deprecated (~=1.2.13)
